BlinkStick-1.2.0.data/scripts/blinkstick
blinkstick/__init__.py
blinkstick/_version.py
blinkstick/blinkstick.py
BlinkStick-1.2.0.dist-info/LICENSE.txt
BlinkStick-1.2.0.dist-info/METADATA
BlinkStick-1.2.0.dist-info/WHEEL
BlinkStick-1.2.0.dist-info/top_level.txt
BlinkStick-1.2.0.dist-info/RECORD
