Metadata-Version: 2.1
Name: BlinkStick
Version: 1.2.0
Summary: Python package to control BlinkStick USB devices.
Home-page: http://pypi.python.org/pypi/BlinkStick/
Author: Arvydas Juskevicius
Author-email: arvydas@arvydas.co.uk
License: LICENSE.txt
Platform: UNKNOWN
Requires-Dist: pywinusb
